LICENSE
MANIFEST.in
README.md
pyproject.toml
docs/AdvisoriesApi.md
docs/AnomaliesApi.md
docs/ApplicationHealthApi.md
docs/EndpointAnalyticsApi.md
docs/EndpointAnalyticsSummaryApi.md
docs/EventsApi.md
docs/FabricFeatureApi.md
docs/FabricsApi.md
docs/ImageIconAPIsApi.md
docs/IntegrationsApi.md
docs/InterfacesApi.md
docs/JobSchedulerApi.md
docs/LicensingAPIsApi.md
docs/LogCollectionApi.md
docs/MetadataApi.md
docs/MicroburstApi.md
docs/NexusInsightsApiV1AdvisoriesDetailsGet200Response.md
docs/NexusInsightsApiV1AdvisoriesDetailsGet200ResponseEntriesInner.md
docs/NexusInsightsApiV1AdvisoriesDetailsGet200ResponseEntriesInnerEntityNameListInner.md
docs/NexusInsightsApiV1AdvisoriesDetailsGet401Response.md
docs/NexusInsightsApiV1AdvisoriesSummaryGet200Response.md
docs/NexusInsightsApiV1AdvisoriesSummaryGet200ResponseEntriesInner.md
docs/NexusInsightsApiV1AdvisoriesTopFabricsGet200Response.md
docs/NexusInsightsApiV1AdvisoriesTopFabricsGet200ResponseEntriesInner.md
docs/NexusInsightsApiV1AlertsTrendGet200Response.md
docs/NexusInsightsApiV1AlertsTrendGet200ResponseEntriesInner.md
docs/NexusInsightsApiV1AlertsTrendGet200ResponseEntriesInnerAlertTrendEntriesInner.md
docs/NexusInsightsApiV1AnomaliesBucketsGet200Response.md
docs/NexusInsightsApiV1AnomaliesBucketsGet200ResponseEntriesInner.md
docs/NexusInsightsApiV1AnomaliesBucketsGet200ResponseEntriesInnerEntriesInner.md
docs/NexusInsightsApiV1AnomaliesBucketsGet200ResponseEntriesInnerEntriesInnerEntriesInner.md
docs/NexusInsightsApiV1AnomaliesDetailsGet200Response.md
docs/NexusInsightsApiV1AnomaliesDetailsGet200ResponseEntriesInner.md
docs/NexusInsightsApiV1AnomaliesDetailsGet200ResponseEntriesInnerCustomData.md
docs/NexusInsightsApiV1AnomaliesDetailsGet200ResponseEntriesInnerEntityNameListInner.md
docs/NexusInsightsApiV1AnomaliesRelatedMetricsGet200Response.md
docs/NexusInsightsApiV1AnomaliesRelatedObjectsGet200Response.md
docs/NexusInsightsApiV1AnomaliesRelatedObjectsGet200ResponseEntriesInner.md
nexuscloud_client.egg-info/PKG-INFO
nexuscloud_client.egg-info/SOURCES.txt
nexuscloud_client.egg-info/dependency_links.txt
nexuscloud_client.egg-info/top_level.txt
