Metadata-Version: 2.1
Name: nexuscloud-client
Version: 1.0.9
Summary: Cisco Nexus Cloud
Author-email: Cisco Nexus Cloud Team <nexuscloud@cisco.com>
Project-URL: Homepage, https://www.intersight.com/nexuscloud
Classifier: Programming Language :: Python :: 3
Classifier: License :: OSI Approved :: Apache Software License
Classifier: Operating System :: OS Independent
Requires-Python: >=3.8
License-File: LICENSE
